<?xml version="1.0"?>
<!DOCTYPE hibernate-mapping PUBLIC
	"-//Hibernate/Hibernate Mapping DTD//EN"
	"http://hibernate.sourceforge.net/hibernate-mapping-3.0.dtd" >

<hibernate-mapping package="resources.bean.report.form">
	<class name="CBlackTransDownload" table="c_black_trans_download_ret">
		<meta attribute="sync-DAO">false</meta>
		<id name="id" type="string" column="SEQ_NO"></id>
    	<property name="sid" column="P_SEQ_NO" type="string" not-null="false" length="20" />
    	<property name="uid" column="P_SEQ_NO2" type="string" not-null="false" length="20" />
    	<property name="retName" column="RET_NAME" type="string" not-null="false" length="400" />
		<property name="etlDate" column="ETL_DATE" type="string" not-null="false" length="8" />
		<property name="dataType" column="DATA_TYPE" type="string" not-null="false" length="2" />
		<property name="gmab" column="GMAB" type="string" not-null="false" length="10" />
		<property name="recId" column="REC_ID" type="string" not-null="false" length="32" />
		<property name="dataDate" column="DATA_DATE" type="string" not-null="false" length="8" />
		<property name="csnm" column="CSNM" type="string" not-null="false" length="32" />
		<property name="ctnm" column="CTNM" type="string" not-null="false" length="512" />
		<property name="citp" column="CITP" type="string" not-null="false" length="60" />
		<property name="ctid" column="CTID" type="string" not-null="false" length="128" />
		<property name="aoitp" column="AOITP" type="string" not-null="false" length="32" />
		<property name="ctnt" column="CTNT" type="string" not-null="false" length="3" />
		<property name="ctvc" column="CTVC" type="string" not-null="false" length="32" />
		<property name="cctl" column="CCTL" type="string" not-null="false" length="800" />
		<property name="ctar" column="CTAR" type="string" not-null="false" length="4000" />
		<property name="ccei" column="CCEI" type="string" not-null="false" length="4000" />
		<property name="cbct" column="CBCT" type="string" not-null="false" length="2" />
		<property name="ocbt" column="OCBT" type="string" not-null="false" length="32" />
		<property name="cbcn" column="CBCN" type="string" not-null="false" length="64" />
		<property name="htdt" column="HTDT" type="string" not-null="false" length="8" />
		<property name="crcd" column="CRCD" type="string" not-null="false" length="4" />
    	<property name="finn" column="FINN" type="string" not-null="false" length="200" />
		<property name="firc" column="FIRC" type="string" not-null="false" length="6" />
		<property name="rltp" column="RLTP" type="string" not-null="false" length="2" />
		<property name="fict" column="FICT" type="string" not-null="false" length="2" />
		<property name="finc" column="FINC" type="string" not-null="false" length="16" />
		<property name="rlfc" column="RLFC" type="string" not-null="false" length="2" />
		<property name="catp" column="CATP" type="string" not-null="false" length="6" />
		<property name="ctac" column="CTAC" type="string" not-null="false" length="64" />
		<property name="oatm" column="OATM" type="string" not-null="false" length="14" />
		<property name="tbnm" column="TBNM" type="string" not-null="false" length="128" />
		<property name="tbit" column="TBIT" type="string" not-null="false" length="6" />
		<property name="tbid" column="TBID" type="string" not-null="false" length="128" />
		<property name="boitp" column="BOITP" type="string" not-null="false" length="32" />
		<property name="tbnt" column="TBNT" type="string" not-null="false" length="3" />
		<property name="tstm" column="TSTM" type="string" not-null="false" length="14" />
		<property name="ticd" column="TICD" type="string" not-null="false" length="256" />
		<property name="rpmt" column="RPMT" type="string" not-null="false" length="2" />
		<property name="rpmn" column="RPMN" type="string" not-null="false" length="500" />
		<property name="tstp" column="TSTP" type="string" not-null="false" length="6" />
		<property name="octt" column="OCTT" type="string" not-null="false" length="2" />
		<property name="ooct" column="OOCT" type="string" not-null="false" length="32" />
		<property name="ocec" column="OCEC" type="string" not-null="false" length="500" />
		<property name="bptc" column="BPTC" type="string" not-null="false" length="500" />
		<property name="tsct" column="TSCT" type="string" not-null="false" length="16" />
		<property name="tsdr" column="TSDR" type="string" not-null="false" length="2" />
		<property name="tdrc" column="TDRC" type="string" not-null="false" length="9" />
		<property name="trcd" column="TRCD" type="string" not-null="false" length="3" />
		<property name="trcdsuffix" column="TRCDSUFFIX" type="string" not-null="false" length="6" />
		<property name="crpp" column="CRPP" type="string" not-null="false" length="256" />
		<property name="crtp" column="CRTP" type="string" not-null="false" length="3" />
		<property name="crat" column="CRAT" type="big_decimal" not-null="false" length="20" />
		<property name="teaAmountCny" column="TRA_AMOUNT_CNY" type="big_decimal" not-null="false" length="20" />
		<property name="teaAmountUsd" column="TRA_AMOUNT_USD" type="big_decimal" not-null="false" length="20" />
		<property name="cfin" column="CFIN" type="string" not-null="false" length="640" />
		<property name="cfct" column="CFCT" type="string" not-null="false" length="2" />
		<property name="cfic" column="CFIC" type="string" not-null="false" length="16" />
		<property name="cfrc" column="CFRC" type="string" not-null="false" length="3" />
		<property name="cfrcsuffix" column="CFRCSUFFIX" type="string" not-null="false" length="6" />
		<property name="tcnm" column="TCNM" type="string" not-null="false" length="128" />
		<property name="tcit" column="TCIT" type="string" not-null="false" length="60" />
		<property name="tcid" column="TCID" type="string" not-null="false" length="128" />
		<property name="coitp" column="COITP" type="string" not-null="false" length="32" />
		<property name="tcat" column="TCAT" type="string" not-null="false" length="6" />
		<property name="tcac" column="TCAC" type="string" not-null="false" length="64" />
		<property name="citpdesc" column="CITPDESC" type="string" not-null="false" length="30" />
		<property name="catm" column="CATM" type="string" not-null="false" length="14" />
		<property name="bitpdesc" column="BITPDESC" type="string" not-null="false" length="30" />
		<property name="crsp" column="CRSP" type="string" not-null="false" length="384" />
		<property name="tictdesc" column="TCITDESC" type="string" not-null="false" length="30" />
		<property name="batchTime" column="BATCH_TIME" type="date" not-null="false" length="34" />
		<!-- add 10191008 zgl -->
		<property name="ccpdt" column="C$CPDT" type="big_decimal" not-null="false" length="8" />
		<property name="cdlno" column="C$DLNO" type="string" not-null="false" length="50" />
		<property name="ccpws" column="C$CPWS" type="string" not-null="false" length="12" />
		<property name="cpimg" column="C$PIMG" type="string" not-null="false" length="60" />
		<property name="cpims" column="C$PIMS" type="string" not-null="false" length="60" />
		<property name="cob" column="C$OB" type="string" not-null="false" length="300" />
		<property name="cpnm" column="C$PNM" type="string" not-null="false" length="840" />
		<property name="cpad" column="C$PAD" type="string" not-null="false" length="960" />
		<property name="cpac" column="C$PAC" type="string" not-null="false" length="102" />
		<property name="cbnm" column="C$BNM" type="string" not-null="false" length="840" />
		<property name="cbad" column="C$BAD" type="string" not-null="false" length="960" />
		<property name="cbac" column="C$BAC" type="string" not-null="false" length="102" />
		<property name="cnr" column="C$NR" type="string" not-null="false" length="4000" />
		<property name="cftag" column="C$FTAG" type="string" not-null="false" length="15" />
		<property name="ctxtf" column="C$TXTF" type="string" not-null="false" length="426" />
		<property name="isBibtcpp" column="IS_BIBTCPP" type="string" not-null="false" length="2" />
		<property name="isMerge" column="IS_MERGE" type="string" not-null="false" length="2" />
		<property name="cmid" column="C$MID" type="string" not-null="false" length="60" />
		<property name="updatePerson" column="UPDATE_PERSON" type="string" not-null="false" length="20" />
		<property name="roleName" column="ROLE_NAME" type="string" not-null="false" length="30" />
		<!-- add 20201210 zgl-->
		<property name="brno" column="BRNO" type="string" not-null="false" length="20" />
	</class>	
</hibernate-mapping>